kittencore-0.0.0.dist-info/WHEEL
kittencore-0.0.0.dist-info/METADATA
kittencore-0.0.0.dist-info/top_level.txt
kittencore-0.0.0.dist-info/RECORD
kitten/_internal/core.cpython-310-i386-linux-gnu.so
