Metadata-Version: 2.2
Name: kittencore
Version: 0.0.0
Summary: kitten
Home-page: https://github.com/kitten-ai/kitten
Author: Kitten AI
Author-email: 
Requires-Dist: pybind11>=2.6
Dynamic: author
Dynamic: home-page
Dynamic: requires-dist
Dynamic: summary
